<?xml version="1.0" encoding="UTF-8"?>
<REQUESTS><item><ID>49817</ID><UF_ID>000091618</UF_ID><uf_source>00-00000069</uf_source><uf_operation_type>Продажа вторичной недвижимости</uf_operation_type><uf_status>Открыт в продажу</uf_status><uf_realty_type>Жилая</uf_realty_type><uf_object_type>000000001</uf_object_type><UF_CONTRAGENT>УТ-00010382</UF_CONTRAGENT><uf_agent>259eec70-6ae1-11e2-b6b7-b74deef9eed9</uf_agent><uf_addr_block>Индекс=236009
КодРегиона=39
Регион=Калининградская обл
РайонГорода=Ленинградский р-н
Город=Калининград г
Улица=Платова ул
Дом=1
Квартира=7
Страна=РОССИЯ
КодСтраны=643
ТипДома=дом
ТипКвартиры=кв.</uf_addr_block><uf_addr_flat>2</uf_addr_flat><uf_add_date>24.11.2016 02:06:34</uf_add_date><uf_update_date>24.11.2016 16:59:56</uf_update_date><uf_etage>2</uf_etage><uf_etage_count>3</uf_etage_count><uf_total_square>20</uf_total_square><uf_living_square>10</uf_living_square><uf_kitchen_square>8</uf_kitchen_square><uf_rooms>2</uf_rooms><UF_CLIENT_PRICE>2000000</UF_CLIENT_PRICE><uf_remont_status>000000009</uf_remont_status><uf_sanusel_type>000000003</uf_sanusel_type><uf_water>000000004</uf_water><uf_heating>000000008</uf_heating><uf_reklama>111</uf_reklama><uf_www>Нет</uf_www><uf_comment/><uf_garage_square>0</uf_garage_square><uf_cellar_square>0</uf_cellar_square><uf_lot_square>0</uf_lot_square><uf_gas/><uf_land_owner_type/><uf_naruzhn_reklama>Нет</uf_naruzhn_reklama><uf_house_type/><uf_entrance/><uf_construct_perm/><uf_owner_rights/><uf_goal_land/><uf_goal/><uf_entry/><uf_electricity/><uf_distance>0</uf_distance><uf_latitude>54.7541</uf_latitude><UF_PRICE_CUST>0</UF_PRICE_CUST><uf_longitude>20.5224</uf_longitude><UF_PRICE_SELL>0</UF_PRICE_SELL><uf_balcony/><uf_phone/><uf_internet/><uf_furniture>Нет</uf_furniture><uf_refrigerator>Нет</uf_refrigerator><uf_parking/><UF_ROOMS_FROM>0</UF_ROOMS_FROM><UF_ROOMS_TO>0</UF_ROOMS_TO><UF_SQUARE_FROM>20</UF_SQUARE_FROM><UF_SQUARE_TO>0</UF_SQUARE_TO><UF_PRICE_FROM>2000000</UF_PRICE_FROM><UF_PRICE_TO>0</UF_PRICE_TO><UF_MATERIAL>1</UF_MATERIAL><uf_photos><item><changed>1</changed><user>259eec70-6ae1-11e2-b6b7-b74deef9eed9</user><photo>0</photo><plan>0</plan><doc>0</doc><preview>1</preview><send>0</send><order>1</order><url>http://portal.invent-realty.ru/upload/pictures/49817/573/1h_400x400.jpg</url></item><item><changed>1</changed><user>259eec70-6ae1-11e2-b6b7-b74deef9eed9</user><photo>1</photo><plan>0</plan><doc>0</doc><preview>0</preview><send>0</send><order>30</order><url>http://portal.invent-realty.ru/upload/pictures/49817/51f/1.jpg</url></item><item><changed>1</changed><user>259eec70-6ae1-11e2-b6b7-b74deef9eed9</user><photo>0</photo><plan>1</plan><doc>0</doc><preview>0</preview><send>0</send><order>30</order><url>http://portal.invent-realty.ru/upload/pictures/49817/0b7/2h_400x400.jpg</url></item><item><changed>1</changed><user>259eec70-6ae1-11e2-b6b7-b74deef9eed9</user><photo>0</photo><plan>0</plan><doc>1</doc><preview>0</preview><send>0</send><order>30</order><url>http://portal.invent-realty.ru/upload/pictures/49817/39c/3.jpg</url></item></uf_photos><UF_URL/><UF_CEILING_HEIGHT>0</UF_CEILING_HEIGHT><UF_SEWERAGE/><uf_price>2000000</uf_price><UF_ADDR_HOUSE>1</UF_ADDR_HOUSE><uf_loggia/><UF_CATEGORY>Категория C</UF_CATEGORY><UF_SEARCH_LINE>УТ-00010449, 259eec58-6ae1-11e2-b6b7-b74deef9eed9, КодРегиона=39 Регион=Калининградская обл РайонГорода=Ленинградский р-н Город=Калининград г Улица=Невского А. ул Страна=РОССИЯ КодСтраны=643, 0, Калининград г, Невского А. ул, Ленинградский р-н</UF_SEARCH_LINE><UF_ENUMERATE_PHOTO/><uf_comment_order>тест</uf_comment_order><answer_1c>000091618</answer_1c></item></REQUESTS>
